{
  "updated": "2026-05-30",
  "exchange_rate": {
    "usd_to_myr": 3.965,
    "fetched_at": "2026-05-30"
  },
  "us_stocks": {
    "tiger_total_usd": 15839.56,
    "tiger_equity_usd": 5817.67,
    "tiger_cash_usd": 10021.88,
    "moomoo_total_usd": 35100.01,
    "moomoo_equity_usd": 17202.51,
    "moomoo_cash_usd": 17897.5,
    "total_usd": 50939.57
  },
  "mplus": {
    "total_myr": 203416.61,
    "holding_pnl_myr": null,
    "dividends_cash_myr": 18204.67,
    "dividends_margin_myr": 21764.55,
    "snapshot_date": "2026-05-30"
  },
  "monthly_usd": [
    {
      "month": "2021-01",
      "tiger": null,
      "moomoo": null,
      "total": null
    },
    {
      "month": "2021-02",
      "tiger": -715.47,
      "moomoo": null,
      "total": -715.47
    },
    {
      "month": "2021-03",
      "tiger": -330.96,
      "moomoo": null,
      "total": -330.96
    },
    {
      "month": "2021-04",
      "tiger": 468.9,
      "moomoo": null,
      "total": 468.9
    },
    {
      "month": "2021-05",
      "tiger": -884.03,
      "moomoo": null,
      "total": -884.03
    },
    {
      "month": "2021-06",
      "tiger": 1227.29,
      "moomoo": null,
      "total": 1227.29
    },
    {
      "month": "2021-07",
      "tiger": 31.55,
      "moomoo": null,
      "total": 31.55
    },
    {
      "month": "2021-08",
      "tiger": 339.44,
      "moomoo": null,
      "total": 339.44
    },
    {
      "month": "2021-09",
      "tiger": -906.7,
      "moomoo": null,
      "total": -906.7
    },
    {
      "month": "2021-10",
      "tiger": 2119.63,
      "moomoo": null,
      "total": 2119.63
    },
    {
      "month": "2021-11",
      "tiger": 678.29,
      "moomoo": null,
      "total": 678.29
    },
    {
      "month": "2021-12",
      "tiger": -497.0,
      "moomoo": null,
      "total": -497.0
    },
    {
      "month": "2022-01",
      "tiger": -1213.57,
      "moomoo": null,
      "total": -1213.57
    },
    {
      "month": "2022-02",
      "tiger": -1560.99,
      "moomoo": null,
      "total": -1560.99
    },
    {
      "month": "2022-03",
      "tiger": 75.92,
      "moomoo": null,
      "total": 75.92
    },
    {
      "month": "2022-04",
      "tiger": -3720.16,
      "moomoo": null,
      "total": -3720.16
    },
    {
      "month": "2022-05",
      "tiger": -1398.31,
      "moomoo": null,
      "total": -1398.31
    },
    {
      "month": "2022-06",
      "tiger": -1689.41,
      "moomoo": null,
      "total": -1689.41
    },
    {
      "month": "2022-07",
      "tiger": 1999.78,
      "moomoo": null,
      "total": 1999.78
    },
    {
      "month": "2022-08",
      "tiger": -659.02,
      "moomoo": null,
      "total": -659.02
    },
    {
      "month": "2022-09",
      "tiger": -1597.92,
      "moomoo": null,
      "total": -1597.92
    },
    {
      "month": "2022-10",
      "tiger": 157.75,
      "moomoo": null,
      "total": 157.75
    },
    {
      "month": "2022-11",
      "tiger": 1028.61,
      "moomoo": null,
      "total": 1028.61
    },
    {
      "month": "2022-12",
      "tiger": -2206.44,
      "moomoo": null,
      "total": -2206.44
    },
    {
      "month": "2023-01",
      "tiger": 1940.85,
      "moomoo": null,
      "total": 1940.85
    },
    {
      "month": "2023-02",
      "tiger": -888.48,
      "moomoo": null,
      "total": -888.48
    },
    {
      "month": "2023-03",
      "tiger": 1703.29,
      "moomoo": null,
      "total": 1703.29
    },
    {
      "month": "2023-04",
      "tiger": 1384.11,
      "moomoo": null,
      "total": 1384.11
    },
    {
      "month": "2023-05",
      "tiger": 1752.53,
      "moomoo": null,
      "total": 1752.53
    },
    {
      "month": "2023-06",
      "tiger": 1196.43,
      "moomoo": null,
      "total": 1196.43
    },
    {
      "month": "2023-07",
      "tiger": 662.41,
      "moomoo": null,
      "total": 662.41
    },
    {
      "month": "2023-08",
      "tiger": -206.75,
      "moomoo": null,
      "total": -206.75
    },
    {
      "month": "2023-09",
      "tiger": -840.94,
      "moomoo": null,
      "total": -840.94
    },
    {
      "month": "2023-10",
      "tiger": -494.15,
      "moomoo": null,
      "total": -494.15
    },
    {
      "month": "2023-11",
      "tiger": 1773.89,
      "moomoo": null,
      "total": 1773.89
    },
    {
      "month": "2023-12",
      "tiger": 801.04,
      "moomoo": null,
      "total": 801.04
    },
    {
      "month": "2024-01",
      "tiger": 68.65,
      "moomoo": null,
      "total": 68.65
    },
    {
      "month": "2024-02",
      "tiger": 1980.0,
      "moomoo": -4.8,
      "total": 1975.2
    },
    {
      "month": "2024-03",
      "tiger": 1703.43,
      "moomoo": 307.16,
      "total": 2010.59
    },
    {
      "month": "2024-04",
      "tiger": -859.95,
      "moomoo": 354.22,
      "total": -505.73
    },
    {
      "month": "2024-05",
      "tiger": 172.06,
      "moomoo": 154.42,
      "total": 326.48
    },
    {
      "month": "2024-06",
      "tiger": -1007.88,
      "moomoo": null,
      "total": -1007.88
    },
    {
      "month": "2024-07",
      "tiger": 1478.24,
      "moomoo": -150.79,
      "total": 1327.45
    },
    {
      "month": "2024-08",
      "tiger": 247.49,
      "moomoo": 559.49,
      "total": 806.98
    },
    {
      "month": "2024-09",
      "tiger": 673.49,
      "moomoo": 11.17,
      "total": 684.66
    },
    {
      "month": "2024-10",
      "tiger": -2162.09,
      "moomoo": -88.58,
      "total": -2250.67
    },
    {
      "month": "2024-11",
      "tiger": -47.34,
      "moomoo": 161.6,
      "total": 114.26
    },
    {
      "month": "2024-12",
      "tiger": -215.89,
      "moomoo": -98.71,
      "total": -314.6
    },
    {
      "month": "2025-01",
      "tiger": 139.57,
      "moomoo": 230.97,
      "total": 370.54
    },
    {
      "month": "2025-02",
      "tiger": -166.75,
      "moomoo": -548.18,
      "total": -714.93
    },
    {
      "month": "2025-03",
      "tiger": -145.89,
      "moomoo": -511.85,
      "total": -657.74
    },
    {
      "month": "2025-04",
      "tiger": -349.28,
      "moomoo": 253.62,
      "total": -95.66
    },
    {
      "month": "2025-05",
      "tiger": -1118.36,
      "moomoo": 1688.5,
      "total": 570.14
    },
    {
      "month": "2025-06",
      "tiger": -321.14,
      "moomoo": 771.29,
      "total": 450.15
    },
    {
      "month": "2025-07",
      "tiger": 27.25,
      "moomoo": 174.91,
      "total": 202.16
    },
    {
      "month": "2025-08",
      "tiger": -140.95,
      "moomoo": -572.58,
      "total": -713.53
    },
    {
      "month": "2025-09",
      "tiger": 176.53,
      "moomoo": 1304.06,
      "total": 1480.59
    },
    {
      "month": "2025-10",
      "tiger": 11.64,
      "moomoo": 1852.99,
      "total": 1864.63
    },
    {
      "month": "2025-11",
      "tiger": 50.44,
      "moomoo": -101.75,
      "total": -51.31
    },
    {
      "month": "2025-12",
      "tiger": 17.3,
      "moomoo": 146.42,
      "total": 163.72
    },
    {
      "month": "2026-01",
      "tiger": 148.21,
      "moomoo": 1407.37,
      "total": 1555.58
    },
    {
      "month": "2026-02",
      "tiger": 82.14,
      "moomoo": -576.64,
      "total": -494.5
    },
    {
      "month": "2026-03",
      "tiger": -401.84,
      "moomoo": -719.14,
      "total": -1120.98
    },
    {
      "month": "2026-04",
      "tiger": 305.71,
      "moomoo": 2628.75,
      "total": 2934.46
    },
    {
      "month": "2026-05",
      "tiger": 48.96,
      "moomoo": 4184.31,
      "total": 4233.27
    }
  ],
  "yearly_summary_usd": [
    {
      "year": 2021,
      "tiger": 1530.94,
      "moomoo": null,
      "total": 1530.94
    },
    {
      "year": 2022,
      "tiger": -10783.76,
      "moomoo": null,
      "total": -10783.76
    },
    {
      "year": 2023,
      "tiger": 8784.23,
      "moomoo": null,
      "total": 8784.23
    },
    {
      "year": 2024,
      "tiger": 2030.21,
      "moomoo": 1205.19,
      "total": 3235.4
    },
    {
      "year": 2025,
      "tiger": -1819.64,
      "moomoo": 4688.39,
      "total": 2868.75
    },
    {
      "year": 2026,
      "tiger": 183.18,
      "moomoo": 6924.63,
      "total": 7107.81
    }
  ],
  "totals_usd": {
    "tiger_all_time": -74.84,
    "moomoo_all_time": 12818.21,
    "total_all_time": 12743.37
  },
  "mplus_snapshots": [
    {
      "date": "2020-12-31",
      "total_myr": 196887.14
    },
    {
      "date": "2021-10-16",
      "total_myr": 199962.06
    },
    {
      "date": "2021-10-29",
      "total_myr": 201710.02
    },
    {
      "date": "2021-12-13",
      "total_myr": 156767.0
    },
    {
      "date": "2021-12-31",
      "total_myr": 156791.67
    },
    {
      "date": "2022-02-04",
      "total_myr": 153559.79
    },
    {
      "date": "2022-02-23",
      "total_myr": 157444.38
    },
    {
      "date": "2022-03-02",
      "total_myr": 154441.85
    },
    {
      "date": "2022-03-30",
      "total_myr": 155798.6
    },
    {
      "date": "2022-04-15",
      "total_myr": 158322.41
    },
    {
      "date": "2022-06-11",
      "total_myr": 151846.5
    },
    {
      "date": "2022-08-05",
      "total_myr": 157388.28
    },
    {
      "date": "2022-11-07",
      "total_myr": 155746.79
    },
    {
      "date": "2022-11-17",
      "total_myr": 162856.11
    },
    {
      "date": "2022-11-24",
      "total_myr": 172105.01
    },
    {
      "date": "2022-12-31",
      "total_myr": 175341.25
    },
    {
      "date": "2023-02-07",
      "total_myr": 184190.79
    },
    {
      "date": "2023-02-21",
      "total_myr": 184727.79
    },
    {
      "date": "2023-03-21",
      "total_myr": 172078.22
    },
    {
      "date": "2023-05-09",
      "total_myr": 172008.54
    },
    {
      "date": "2023-05-30",
      "total_myr": 168687.16
    },
    {
      "date": "2023-07-12",
      "total_myr": 172930.54
    },
    {
      "date": "2023-08-07",
      "total_myr": 179392.14
    },
    {
      "date": "2023-08-31",
      "total_myr": 183804.24
    },
    {
      "date": "2023-10-11",
      "total_myr": 181951.1
    },
    {
      "date": "2023-11-02",
      "total_myr": 183530.82
    },
    {
      "date": "2023-12-28",
      "total_myr": 186770.6
    },
    {
      "date": "2024-03-07",
      "total_myr": 190550.61
    },
    {
      "date": "2024-04-05",
      "total_myr": 193846.5
    },
    {
      "date": "2024-05-10",
      "total_myr": 195481.45
    },
    {
      "date": "2024-05-31",
      "total_myr": 204724.7
    },
    {
      "date": "2024-06-14",
      "total_myr": 224000.49
    },
    {
      "date": "2024-08-03",
      "total_myr": 222455.16
    },
    {
      "date": "2024-08-20",
      "total_myr": 221000.97
    },
    {
      "date": "2024-10-09",
      "total_myr": 247847.08
    },
    {
      "date": "2024-11-07",
      "total_myr": 256482.27
    },
    {
      "date": "2024-12-31",
      "total_myr": 259298.26
    },
    {
      "date": "2025-02-07",
      "total_myr": 252586.39
    },
    {
      "date": "2025-05-02",
      "total_myr": 250123.19
    },
    {
      "date": "2025-06-12",
      "total_myr": 263271.61
    },
    {
      "date": "2025-08-07",
      "total_myr": 264478.24
    },
    {
      "date": "2025-09-21",
      "total_myr": 271122.56
    },
    {
      "date": "2025-12-31",
      "total_myr": 273121.68
    },
    {
      "date": "2026-04-01",
      "total_myr": 172567.31
    },
    {
      "date": "2026-05-08",
      "total_myr": 194269.81
    },
    {
      "date": "2026-05-24",
      "total_myr": 203845.99
    },
    {
      "date": "2026-05-30",
      "total_myr": 203416.61
    }
  ]
}